git_llm_commit/__init__.py
git_llm_commit/llm_commit.py
git_llm_commit-2.1.0.dist-info/METADATA
git_llm_commit-2.1.0.dist-info/WHEEL
git_llm_commit-2.1.0.dist-info/entry_points.txt
git_llm_commit-2.1.0.dist-info/licenses/LICENSE
git_llm_commit-2.1.0.dist-info/RECORD
