Metadata-Version: 2.4
Name: git-llm-commit
Version: 2.1.0
Summary: Generate Conventional Commit messages from your staged changes using an LLM
Author-email: Bryan Lackey <lackeyjb1@users.noreply.github.com>
License-File: LICENSE
Requires-Python: >=3.12
Requires-Dist: openai>=1.61.0
Requires-Dist: python-dotenv>=1.0.1
